swh/loader/git/__init__.py
swh/loader/git/base.py
swh/loader/git/converters.py
swh/loader/git/directory.py
swh/loader/git/from_disk.py
swh/loader/git/loader.py
swh/loader/git/py.typed
swh/loader/git/tasks.py
swh/loader/git/utils.py
swh/loader/git/tests/__init__.py
swh/loader/git/tests/conftest.py
swh/loader/git/tests/test_converters.py
swh/loader/git/tests/test_directory.py
swh/loader/git/tests/test_from_disk.py
swh/loader/git/tests/test_loader.py
swh/loader/git/tests/test_tasks.py
swh/loader/git/tests/test_tasks_directory.py
swh/loader/git/tests/test_utils.py
swh/loader/git/tests/data/testrepo.tgz
swh/loader/git/tests/data/git-repos/example-submodule.bundle
swh_loader_git-2.14.2.dist-info/licenses/AUTHORS
swh_loader_git-2.14.2.dist-info/licenses/LICENSE
swh_loader_git-2.14.2.dist-info/METADATA
swh_loader_git-2.14.2.dist-info/WHEEL
swh_loader_git-2.14.2.dist-info/entry_points.txt
swh_loader_git-2.14.2.dist-info/top_level.txt
swh_loader_git-2.14.2.dist-info/RECORD
