Metadata-Version: 2.4
Name: swh.loader.git
Version: 2.14.2
Summary: Software Heritage git loader
Author-email: Software Heritage developers <swh-devel@inria.fr>
Project-URL: Homepage, https://gitlab.softwareheritage.org/swh/devel/swh-loader-git
Project-URL: Bug Reports, https://gitlab.softwareheritage.org/swh/devel/swh-loader-git/-/issues
Project-URL: Funding, https://www.softwareheritage.org/donate
Project-URL: Documentation, https://docs.softwareheritage.org/devel/swh-loader-git/
Project-URL: Source, https://gitlab.softwareheritage.org/swh/devel/swh-loader-git.git
Classifier: Programming Language :: Python :: 3
Classifier: Intended Audience :: Developers
Classifier: License :: OSI Approved :: GNU General Public License v3 (GPLv3)
Classifier: Operating System :: OS Independent
Classifier: Development Status :: 5 - Production/Stable
Classifier: Programming Language :: Python :: Implementation :: CPython
Classifier: Programming Language :: Python :: Implementation :: PyPy
Requires-Python: >=3.10
License-File: LICENSE
License-File: AUTHORS
Requires-Dist: dulwich>=0.25.0
Requires-Dist: retrying
Requires-Dist: click
Requires-Dist: swh.core>=4.5.3
Requires-Dist: swh.loader.core>=5.24.0
Requires-Dist: swh.model>=8.1.0
Requires-Dist: swh.scheduler>=0.0.39
Requires-Dist: swh.storage>=2.4.1
Provides-Extra: testing
Requires-Dist: dulwich>=0.25.0; extra == "testing"
Requires-Dist: retrying; extra == "testing"
Requires-Dist: click; extra == "testing"
Requires-Dist: swh.core>=4.5.3; extra == "testing"
Requires-Dist: swh.loader.core>=5.24.0; extra == "testing"
Requires-Dist: swh.model>=8.1.0; extra == "testing"
Requires-Dist: swh.scheduler>=0.0.39; extra == "testing"
Requires-Dist: swh.storage>=2.4.1; extra == "testing"
Requires-Dist: celery-types; extra == "testing"
Requires-Dist: pytest>=8.1; extra == "testing"
Requires-Dist: pytest-mock; extra == "testing"
Requires-Dist: requests_mock; extra == "testing"
Requires-Dist: swh.loader.core[testing]>=5.24.0; extra == "testing"
Requires-Dist: swh.scheduler[pytest]>=3.1.0; extra == "testing"
Requires-Dist: swh.storage[pytest]>=3.1.0; extra == "testing"
Requires-Dist: types-Deprecated; extra == "testing"
Requires-Dist: types-urllib3; extra == "testing"
Dynamic: license-file
